claude_telemetry/__init__.py
claude_telemetry/cli.py
claude_telemetry/hooks.py
claude_telemetry/logfire_adapter.py
claude_telemetry/runner.py
claude_telemetry/sentry_adapter.py
claude_telemetry/sync.py
claude_telemetry/telemetry.py
claude_telemetry/helpers/__init__.py
claude_telemetry/helpers/logger.py
claude_telemetry-0.5.0.dist-info/licenses/LICENSE
claude_telemetry-0.5.0.dist-info/METADATA
claude_telemetry-0.5.0.dist-info/WHEEL
claude_telemetry-0.5.0.dist-info/entry_points.txt
claude_telemetry-0.5.0.dist-info/top_level.txt
claude_telemetry-0.5.0.dist-info/RECORD
