Metadata-Version: 2.4
Name: claude_telemetry
Version: 0.5.0
Summary: OpenTelemetry instrumentation for Claude agents
Author-email: Nick Garvey <nick@technick.ai>
License: MIT
Project-URL: Homepage, https://github.com/TechNickAI/claude_telemetry
Project-URL: Repository, https://github.com/TechNickAI/claude_telemetry
Project-URL: Issues, https://github.com/TechNickAI/claude_telemetry/issues
Classifier: Development Status :: 3 - Alpha
Classifier: Intended Audience :: Developers
Classifier: License :: OSI Approved :: MIT License
Classifier: Programming Language :: Python :: 3
Classifier: Programming Language :: Python :: 3.10
Classifier: Programming Language :: Python :: 3.11
Classifier: Programming Language :: Python :: 3.12
Classifier: Programming Language :: Python :: 3.13
Requires-Python: >=3.10
License-File: LICENSE
Requires-Dist: claude-agent-sdk
Requires-Dist: loguru
Requires-Dist: opentelemetry-api
Requires-Dist: opentelemetry-exporter-otlp-proto-http
Requires-Dist: opentelemetry-sdk
Requires-Dist: pydantic
Requires-Dist: python-dotenv
Requires-Dist: rich
Requires-Dist: typer
Provides-Extra: logfire
Requires-Dist: logfire>=4.0.0; extra == "logfire"
Provides-Extra: all
Requires-Dist: logfire>=4.0.0; extra == "all"
Provides-Extra: dev
Requires-Dist: pytest>=7.0.0; extra == "dev"
Requires-Dist: pytest-asyncio>=0.21.0; extra == "dev"
Requires-Dist: pytest-mock>=3.10.0; extra == "dev"
Requires-Dist: ruff>=0.1.0; extra == "dev"
Dynamic: license-file
